pulumi_kubernetes_coredns/__init__.py
pulumi_kubernetes_coredns/_inputs.py
pulumi_kubernetes_coredns/_utilities.py
pulumi_kubernetes_coredns/core_dns.py
pulumi_kubernetes_coredns/outputs.py
pulumi_kubernetes_coredns/provider.py
pulumi_kubernetes_coredns/pulumi-plugin.json
pulumi_kubernetes_coredns/py.typed
pulumi_kubernetes_coredns-0.1.0.dist-info/METADATA
pulumi_kubernetes_coredns-0.1.0.dist-info/WHEEL
pulumi_kubernetes_coredns-0.1.0.dist-info/top_level.txt
pulumi_kubernetes_coredns-0.1.0.dist-info/RECORD
