Metadata-Version: 2.1
Name: pulumi_kubernetes_coredns
Version: 0.1.0
Summary: Strongly-typed CoreDNS installation
License: Apache-2.0
Project-URL: Homepage, https://pulumi.io
Project-URL: Repository, https://github.com/pulumi/pulumi-kubernetes-coredns
Keywords: pulumi,kubernetes,coredns,kind/component,category/infrastructure
Requires-Python: >=3.9
Requires-Dist: parver>=0.2.1
Requires-Dist: pulumi<4.0.0,>=3.0.0
Requires-Dist: pulumi-kubernetes<5.0.0,>=4.19.0
Requires-Dist: semver>=2.8.1
Requires-Dist: typing-extensions>=4.11; python_version < "3.11"
